[
  {
    "name": "dev",
    "version": "dev",
    "url": "https://actions.docs.ansys.com/version/dev/"
  },
  {
    "name": "10.3 (stable)",
    "version": "10.3",
    "url": "https://actions.docs.ansys.com/version/stable/"
  },
  {
    "name": "10.2",
    "version": "10.2",
    "url": "https://actions.docs.ansys.com/version/10.2/"
  },
  {
    "name": "10.1",
    "version": "10.1",
    "url": "https://actions.docs.ansys.com/version/10.1/"
  },
  {
    "name": "Older version",
    "version": "N/A",
    "url": "https://actions.docs.ansys.com/version/"
  }
]